sdj_remotetools/__init__.py
sdj_remotetools/rcat.py
sdj_remotetools/rexec.py
sdj_remotetools/rlist.py
sdj_remotetools/utils.py
sdj_remotetools-0.5.0.dist-info/LICENSE.md
sdj_remotetools-0.5.0.dist-info/METADATA
sdj_remotetools-0.5.0.dist-info/WHEEL
sdj_remotetools-0.5.0.dist-info/entry_points.txt
sdj_remotetools-0.5.0.dist-info/RECORD
