Metadata-Version: 2.1
Name: sdj-remotetools
Version: 0.5.0
Summary: Collection of remote management tools through SSH
Home-page: https://github.com/sdejongh/sdj_remotetools
License: MIT
Keywords: cli,ssh,cat,remote,command-line
Author: Steve De Jongh
Author-email: dejongh.st@gmail.com
Requires-Python: >=3.9,<4.0
Classifier: Development Status :: 4 - Beta
Classifier: Environment :: Console
Classifier: License :: OSI Approved :: MIT License
Classifier: Programming Language :: Python :: 3
Classifier: Programming Language :: Python :: 3.9
Classifier: Programming Language :: Python :: 3.10
Classifier: Programming Language :: Python :: 3.11
Classifier: Programming Language :: Python :: 3.12
Classifier: Topic :: Utilities
Requires-Dist: fabric (>=3.2.2,<4.0.0)
Requires-Dist: paramiko (>=3.3.1,<4.0.0)
Requires-Dist: rich (>=13.7.0,<14.0.0)
Project-URL: Bug Tracker, https://github.com/sdejongh/sdj_remotetools/issues
Project-URL: Repository, https://github.com/sdejongh/sdj_remotetools
